README.md
setup.py
hackerpaper/__init__.py
hackerpaper/__main__.py
hackerpaper/cli.py
hackerpaper/request.py
hackerpaper/urls.py
hackerpaper.egg-info/PKG-INFO
hackerpaper.egg-info/SOURCES.txt
hackerpaper.egg-info/dependency_links.txt
hackerpaper.egg-info/entry_points.txt
hackerpaper.egg-info/top_level.txt