Metadata-Version: 2.1
Name: hackerpaper
Version: 0.0.2
Summary: Hacker News to Instapaper
Home-page: http://packages.python.org/hackerpaper
Author: Liam Scalzulli
Author-email: liamscalzulli@gmail.com
License: BSD
Keywords: hackernews,instapaper,cli
Platform: UNKNOWN
Classifier: Development Status :: 3 - Alpha
Classifier: Topic :: Utilities
Classifier: License :: OSI Approved :: BSD License
Requires-Python: >=3.7
